goodboy_flask/__init__.py
goodboy_flask-0.1.0.dist-info/LICENSE
goodboy_flask-0.1.0.dist-info/WHEEL
goodboy_flask-0.1.0.dist-info/METADATA
goodboy_flask-0.1.0.dist-info/RECORD
